loongchain/__init__.py
loongchain/chain.py
loongchain-0.6.dist-info/METADATA
loongchain-0.6.dist-info/WHEEL
loongchain-0.6.dist-info/licenses/LICENSE
loongchain-0.6.dist-info/RECORD
